{
  "$schema": "handbook-course-v1",
  "code": "ASL2203F",
  "title": "Applied Sociolinguistics (Extended)",
  "department": "african-languages-and-literatures",
  "credits": 24,
  "nqf_level": 6,
  "year_level": 2,
  "semester": "S1",
  "semester_code": "F",
  "convener": "TBA",
  "prerequisites": {
    "text": "None (extended programme students only).",
    "parsed": {
      "type": "text_only",
      "codes": []
    }
  },
  "corequisites": [
    "ASL2202F"
  ],
  "outline": "The purpose of this course is to augment and support its co -requisite course: ASL2202F African Political Thought. It aims to improve students’ performance by enhancing their grasp of key ideas and concepts, and by developing their mastery of the disciplina ry discourse. It provides additional pedagogic enrichment in the form of regular Plus Tuts that extend into Writing Hub exercises and consultations. In these tutorials, students will receive explicit support around the co -requisite course assignments and detailed feedback on their written work.",
  "lecture_times": "6th period.",
  "dp_requirements": "None.",
  "assessment": "This course will be assessed on a Pass/Fail basis. In order to receive a pass grade, students will be required to complete: coursework 100% comprising of tutorial assessment, other written work and participation.",
  "is_humanities_course": true
}
